MANIFEST.in
README
setup.py
bin/pluginbuilder
pluginbuilder/__init__.py
pluginbuilder/build_plugin.py
pluginbuilder/util.py
pluginbuilder.egg-info/PKG-INFO
pluginbuilder.egg-info/SOURCES.txt
pluginbuilder.egg-info/dependency_links.txt
pluginbuilder.egg-info/not-zip-safe
pluginbuilder.egg-info/requires.txt
pluginbuilder.egg-info/top_level.txt
pluginbuilder/bootstrap/__init__.py
pluginbuilder/bootstrap/argv_inject.py
pluginbuilder/bootstrap/boot_aliasplugin.py
pluginbuilder/bootstrap/boot_plugin.py
pluginbuilder/bootstrap/disable_linecache.py
pluginbuilder/bootstrap/import_encodings.py
pluginbuilder/bootstrap/path_inject.py
pluginbuilder/bootstrap/site_packages.py
pluginbuilder/bundletemplate/__init__.py
pluginbuilder/bundletemplate/plist_template.py
pluginbuilder/bundletemplate/setup.py
pluginbuilder/bundletemplate/lib/site.py
pluginbuilder/bundletemplate/src/main.m
pluginbuilder/recipes/__init__.py
pluginbuilder/recipes/cjkcodecs.py
pluginbuilder/recipes/docutils.py
pluginbuilder/recipes/email.py
pluginbuilder/recipes/matplotlib.py
pluginbuilder/recipes/numpy.py
pluginbuilder/recipes/pydoc.py
pluginbuilder/recipes/pygame.py
pluginbuilder/recipes/pyopengl.py
pluginbuilder/recipes/scipy.py
pluginbuilder/recipes/sip.py
pluginbuilder/recipes/virtualenv.py
pluginbuilder/recipes/PIL/__init__.py
pluginbuilder/recipes/PIL/prescript.py