Metadata-Version: 1.0
Name: pluginbuilder
Version: 1.1.0
Summary: Create standalone Mac OS X plugins with Python
Home-page: http://bitbucket.org/hsoft/pluginbuilder
Author: Virgil Dupras
Author-email: hsoft@hardcoded.net
License: MIT or PSF License
Download-URL: http://pypi.python.org/pypi/pluginbuilder
Platform: MacOS X
Classifier: Environment :: Console
Classifier: Environment :: MacOS X :: Cocoa
Classifier: Intended Audience :: Developers
Classifier: License :: OSI Approved :: MIT License
Classifier: Operating System :: MacOS :: MacOS X
Classifier: Programming Language :: Python
Classifier: Programming Language :: Python :: 3
Classifier: Programming Language :: Python :: 3.2
Classifier: Programming Language :: Objective C
Classifier: Topic :: Software Development :: Libraries :: Python Modules
Classifier: Topic :: Software Development :: User Interfaces
Classifier: Topic :: Software Development :: Build Tools
